psd/iPad-mini-Starlight-Portrait.psd
psd/iPadPro13-M4-Silver-Portrait.psd
psd/iPhone17ProMax-DeepBlue-Portrait.psd
snap2store/__init__.py
snap2store/ipad_batch.py
snap2store/ipad_mini_batch.py
snap2store/iphone_batch.py
snap2store/main.py
snap2store-0.2.0.dist-info/licenses/LICENSE
snap2store-0.2.0.dist-info/METADATA
snap2store-0.2.0.dist-info/WHEEL
snap2store-0.2.0.dist-info/entry_points.txt
snap2store-0.2.0.dist-info/top_level.txt
snap2store-0.2.0.dist-info/RECORD
