Metadata-Version: 2.4
Name: snap2store
Version: 0.2.0
Summary: Auto add device frames to iOS/iPadOS screenshots for App Store.
Author-email: Lilong Zhang <and2long@gmail.com>
License: MIT License
Project-URL: Homepage, https://github.com/and2long/snap2store
Project-URL: Bug Tracker, https://github.com/and2long/snap2store/issues
Keywords: ios,ipad,screenshot,app-store,developer-tools
Classifier: Development Status :: 4 - Beta
Classifier: Environment :: Console
Classifier: Intended Audience :: Developers
Classifier: License :: OSI Approved :: MIT License
Classifier: Programming Language :: Python :: 3
Classifier: Programming Language :: Python :: 3.8
Classifier: Programming Language :: Python :: 3.9
Classifier: Programming Language :: Python :: 3.10
Classifier: Programming Language :: Python :: 3.11
Classifier: Programming Language :: Python :: 3.12
Classifier: Topic :: Multimedia :: Graphics
Classifier: Topic :: Software Development :: Libraries :: Python Modules
Classifier: Topic :: Utilities
Requires-Python: >=3.8
License-File: LICENSE
Requires-Dist: Pillow>=9.0.0
Requires-Dist: psd-tools>=1.9.0
Dynamic: license-file
